tensor_engine/__init__.py
tensor_engine/engine.py
tensor_engine/object.py
tensor_engine/window.py
tensor_engine-0.1.0.dist-info/METADATA
tensor_engine-0.1.0.dist-info/WHEEL
tensor_engine-0.1.0.dist-info/top_level.txt
tensor_engine-0.1.0.dist-info/RECORD
