Metadata-Version: 2.4
Name: tensor-engine
Version: 0.1.0
Summary: A Cool Terminal Game Engine built with Python.
Author: MrPsyghost (Shivay)
Author-email: shivaypuri2000@gmail.com
Project-URL: YouTube, https://www.youtube.com/@MrPsyghost
Keywords: game engine,tensor engine,terminal game engine,terminal,tensor,game,engine,cli,cli game engine
Classifier: Development Status :: 4 - Beta
Classifier: Intended Audience :: Science/Research
Classifier: Topic :: Scientific/Engineering :: Artificial Intelligence
Classifier: Programming Language :: Python :: 3.10
Classifier: Programming Language :: Python :: 3.11
Classifier: Operating System :: OS Independent
Requires-Python: >=3.10
Requires-Dist: pynput>=1.8.0
Dynamic: author
Dynamic: author-email
Dynamic: classifier
Dynamic: keywords
Dynamic: project-url
Dynamic: requires-dist
Dynamic: requires-python
Dynamic: summary
